cdk_pgstac/__init__.py
cdk_pgstac/py.typed
cdk_pgstac/_jsii/__init__.py
cdk_pgstac/_jsii/cdk-pgstac@4.2.3.jsii.tgz
cdk_pgstac-4.2.3.dist-info/LICENSE
cdk_pgstac-4.2.3.dist-info/METADATA
cdk_pgstac-4.2.3.dist-info/WHEEL
cdk_pgstac-4.2.3.dist-info/top_level.txt
cdk_pgstac-4.2.3.dist-info/RECORD
