Metadata-Version: 2.1
Name: cdk-pgstac
Version: 4.2.3
Summary: A set of constructs deploying pgSTAC with CDK
Home-page: https://github.com/developmentseed/cdk-pgstac.git
Author: Anthony Lukach<anthony@developmentseed.org>
License: ISC
Project-URL: Source, https://github.com/developmentseed/cdk-pgstac.git
Platform: UNKNOWN
Classifier: Intended Audience :: Developers
Classifier: Operating System :: OS Independent
Classifier: Programming Language :: JavaScript
Classifier: Programming Language :: Python :: 3 :: Only
Classifier: Programming Language :: Python :: 3.7
Classifier: Programming Language :: Python :: 3.8
Classifier: Programming Language :: Python :: 3.9
Classifier: Programming Language :: Python :: 3.10
Classifier: Typing :: Typed
Classifier: Development Status :: 4 - Beta
Classifier: License :: OSI Approved
Requires-Python: ~=3.7
License-File: LICENSE
Requires-Dist: aws-cdk-lib (<3.0.0,>=2.75.0)
Requires-Dist: aws-cdk.aws-apigatewayv2-integrations-alpha (<3.0.0,>=2.47.0.a0)
Requires-Dist: aws-cdk.aws-lambda-python-alpha (<3.0.0,>=2.47.0.a0)
Requires-Dist: constructs (<11.0.0,>=10.1.113)
Requires-Dist: jsii (<2.0.0,>=1.69.0)
Requires-Dist: publication (>=0.0.3)
Requires-Dist: typeguard (~=2.13.3)
